setup.py
kallikrein/__init__.py
kallikrein/expectable.py
kallikrein/expectation.py
kallikrein/match_result.py
kallikrein/matcher.py
kallikrein/unsafe.py
kallikrein.egg-info/PKG-INFO
kallikrein.egg-info/SOURCES.txt
kallikrein.egg-info/dependency_links.txt
kallikrein.egg-info/entry_points.txt
kallikrein.egg-info/requires.txt
kallikrein.egg-info/top_level.txt
kallikrein/matchers/__init__.py
kallikrein/matchers/any.py
kallikrein/matchers/comparison.py
kallikrein/matchers/contain.py
kallikrein/matchers/either.py
kallikrein/matchers/empty.py
kallikrein/matchers/eval.py
kallikrein/matchers/foldable.py
kallikrein/matchers/forall.py
kallikrein/matchers/length.py
kallikrein/matchers/lines.py
kallikrein/matchers/maybe.py
kallikrein/matchers/throw.py
kallikrein/matchers/typed.py
kallikrein/run/__init__.py
kallikrein/run/cli.py
kallikrein/run/config.py
kallikrein/run/data.py
kallikrein/run/line.py
kallikrein/run/lookup_loc.py
kallikrein/run/main.py
kallikrein/run/result.py
kallikrein/util/__init__.py
kallikrein/util/string.py