Metadata-Version: 1.0
Name: kallikrein
Version: 0.16.2
Summary: spec framework
Home-page: https://github.com/tek/kallikrein
Author: Torsten Schmits
Author-email: torstenschmits@gmail.com
License: MIT
Platform: UNKNOWN
